Metadata-Version: 2.1
Name: django-restful-admin
Version: 1.1.3
Summary: Python Django RestFul Admin
Home-page: https://github.com/amirasaran/django-restful-admin
Author: Amir Mohsen Asaran
Author-email: admin@mihanmail.com
License: MIT
Keywords: django restful admin
Platform: UNKNOWN
Classifier: Development Status :: 4 - Beta
Classifier: Intended Audience :: Developers
Classifier: Topic :: Software Development :: Build Tools
Classifier: License :: OSI Approved :: MIT License
Classifier: Programming Language :: Python :: 2
Classifier: Programming Language :: Python :: 2.7
Classifier: Programming Language :: Python :: 3
Classifier: Programming Language :: Python :: 3.3
Classifier: Programming Language :: Python :: 3.4
Classifier: Programming Language :: Python :: 3.5
Requires-Dist: django (>=2.0.0)
Requires-Dist: djangorestframework (>=3.0.0)
